LICENSE
README.rst
setup.py
lamart_sendbox_sdk.egg-info/PKG-INFO
lamart_sendbox_sdk.egg-info/SOURCES.txt
lamart_sendbox_sdk.egg-info/dependency_links.txt
lamart_sendbox_sdk.egg-info/requires.txt
lamart_sendbox_sdk.egg-info/top_level.txt
sendbox_sdk/__init__.py
sendbox_sdk/api.py
sendbox_sdk/base.py
sendbox_sdk/const.py
sendbox_sdk/utils.py