Metadata-Version: 2.1
Name: lamart-sendbox-sdk
Version: 0.1.1
Summary: SDK for Mail.ru Sendbox rest api / re-uploaded by lamart 
Home-page: https://github.com/Jacob-ru/PySendboxSDK
Author: Yasha Mikhoparkin
Author-email: tb@lamart.site
License: MIT
Platform: UNKNOWN
Classifier: Development Status :: 2 - Pre-Alpha
Classifier: License :: OSI Approved :: MIT License
Classifier: Programming Language :: Python
Classifier: Programming Language :: Python :: 3.4
Classifier: Programming Language :: Python :: 3.5
Classifier: Programming Language :: Python :: 3.6
Classifier: Programming Language :: Python :: 3.7
License-File: LICENSE
